MANIFEST.in
README.rst
setup.cfg
setup.py
django_television.egg-info/PKG-INFO
django_television.egg-info/SOURCES.txt
django_television.egg-info/dependency_links.txt
django_television.egg-info/requires.txt
django_television.egg-info/top_level.txt
television/__init__.py
television/app.py
television/consumers.py
television/decorators.py
television/exceptions.py
television/registry.py
television/routing.py
television/utils.py
television/static/django-television.js
television/static/django-television.js.map